MANIFEST.in
setup.py
avi/__init__.py
avi/migrationtools/__init__.py
avi/migrationtools/avi_converter.py
avi/migrationtools/avi_migration_utils.py
avi/migrationtools/avi_orphan_object.py
avi/migrationtools/avi_rest_lib.py
avi/migrationtools/config_patch.py
avi/migrationtools/custom_config.py
avi/migrationtools/pb_attributes.yaml
avi/migrationtools/scp_util.py
avi/migrationtools/setup.py
avi/migrationtools/vs_filter.py
avi/migrationtools/ace_converter/__init__.py
avi/migrationtools/ace_converter/ace_config_converter.py
avi/migrationtools/ace_converter/ace_constants.py
avi/migrationtools/ace_converter/ace_converter.py
avi/migrationtools/ace_converter/ace_parser.py
avi/migrationtools/ace_converter/ace_utils.py
avi/migrationtools/ace_converter/monitor_converter.py
avi/migrationtools/ace_converter/persistance_conversion.py
avi/migrationtools/ace_converter/pool_converter.py
avi/migrationtools/ace_converter/ssl_converter.py
avi/migrationtools/ace_converter/vs_converter.py
avi/migrationtools/ace_converter/test/dummy_input.json
avi/migrationtools/ace_converter/test/test_input.json
avi/migrationtools/ansible/__init__.py
avi/migrationtools/ansible/ansible_config_converter.py
avi/migrationtools/ansible/ansible_constant.py
avi/migrationtools/ansible/ansible_traffic_generation.py
avi/migrationtools/ansible/avi_config_to_ansible.py
avi/migrationtools/common/avi_resource_types.yaml
avi/migrationtools/f5_converter/__init__.py
avi/migrationtools/f5_converter/ciphers_converter.py
avi/migrationtools/f5_converter/clone_cross_tenant_obj.py
avi/migrationtools/f5_converter/command_status.yaml
avi/migrationtools/f5_converter/config.yaml
avi/migrationtools/f5_converter/conversion_util.py
avi/migrationtools/f5_converter/converter_constants.py
avi/migrationtools/f5_converter/datagroup_converter.py
avi/migrationtools/f5_converter/f5_config_converter.py
avi/migrationtools/f5_converter/f5_config_parser.py
avi/migrationtools/f5_converter/f5_converter.py
avimigrationtools.egg-info/PKG-INFO
avimigrationtools.egg-info/SOURCES.txt
avimigrationtools.egg-info/dependency_links.txt
avimigrationtools.egg-info/requires.txt
avimigrationtools.egg-info/top_level.txt